{
  "CTLA01H3-F-20259": {
    "courseId": "6818a9640982ec3a6ff6e1bf",
    "courseTitle": "Foundations in Effective Academic Communication",
    "code": "CTLA01H3",
    "courseDescription": "This highly interactive course for English Language Learners who find Academic English a challenge aims to fast-track the development of critical thinking, reading, writing and oral communication skills. Through emphasizing academic writing and rapid expansion of vocabulary, students will gain practical experience with university-level academic texts and assignment expectations.",
    "prerequisite": "No more than 10.0 credits completed. Students are required to take a diagnostic test of academic English skills to be conducted by the English Language Development Support,  Centre for Teaching and Learning, in advance of the first day of class.",
    "corequisite": "",
    "exclusion": "",
    "recommendedPreparation": "",
    "section": "F",
    "session": "20259",
    "deliveryInstructions": null,
    "breadthCategories": "Arts, Literature & Language",
    "distributionCategories": "",
    "meetings": {
      "LEC-01": {
        "schedule": {
          "TU-0": {
            "meetingDay": "TU",
            "meetingStartTime": "11:00",
            "meetingEndTime": "13:00",
            "meetingScheduleId": "0",
            "assignedRoom1": "BV",
            "assignedRoom2": "BV"
          }
        },
        "instructors": {
          "0": {
            "instructorId": "0",
            "firstName": "Elaine",
            "lastName": "Khoo"
          }
        },
        "meetingId": "LEC01",
        "teachingMethod": "LEC",
        "sectionNumber": "01",
        "subtitle": "",
        "cancel": "",
        "waitlist": "Y",
        "deliveryMode": "INPER",
        "online": "In Person",
        "enrollmentCapacity": "40",
        "actualEnrolment": "36",
        "actualWaitlist": "0",
        "enrollmentIndicator": "RP",
        "meetingStatusNotes": null,
        "enrollmentControls": [
          {
            "postId": "1",
            "postCode": "",
            "postName": "",
            "subjectId": "1",
            "subjectCode": "*",
            "subjectName": "All",
            "designationId": "1",
            "designationCode": "*",
            "designationName": "All",
            "yearOfStudy": "1",
            "typeOfProgramId": "1",
            "typeOfProgramCode": "*",
            "typeOfProgramName": "All",
            "primaryOrgId": "1",
            "primaryOrgCode": "SCAR",
            "primaryOrgName": "University of Toronto Scarborough",
            "secondaryOrgId": "1",
            "secondaryOrgCode": "*",
            "secondaryOrgName": "All",
            "assocOrgId": "1",
            "assocOrgCode": "*",
            "assocOrgName": "All",
            "adminOrgId": "1",
            "adminOrgCode": "*",
            "adminOrgName": "All"
          },
          {
            "postId": "2",
            "postCode": "",
            "postName": "",
            "subjectId": "1",
            "subjectCode": "*",
            "subjectName": "All",
            "designationId": "1",
            "designationCode": "*",
            "designationName": "All",
            "yearOfStudy": "2",
            "typeOfProgramId": "1",
            "typeOfProgramCode": "*",
            "typeOfProgramName": "All",
            "primaryOrgId": "1",
            "primaryOrgCode": "SCAR",
            "primaryOrgName": "University of Toronto Scarborough",
            "secondaryOrgId": "1",
            "secondaryOrgCode": "*",
            "secondaryOrgName": "All",
            "assocOrgId": "1",
            "assocOrgCode": "*",
            "assocOrgName": "All",
            "adminOrgId": "1",
            "adminOrgCode": "*",
            "adminOrgName": "All"
          },
          {
            "postId": "3",
            "postCode": "",
            "postName": "",
            "subjectId": "1",
            "subjectCode": "*",
            "subjectName": "All",
            "designationId": "1",
            "designationCode": "*",
            "designationName": "All",
            "yearOfStudy": "3",
            "typeOfProgramId": "1",
            "typeOfProgramCode": "*",
            "typeOfProgramName": "All",
            "primaryOrgId": "1",
            "primaryOrgCode": "SCAR",
            "primaryOrgName": "University of Toronto Scarborough",
            "secondaryOrgId": "1",
            "secondaryOrgCode": "*",
            "secondaryOrgName": "All",
            "assocOrgId": "1",
            "assocOrgCode": "*",
            "assocOrgName": "All",
            "adminOrgId": "1",
            "adminOrgCode": "*",
            "adminOrgName": "All"
          }
        ]
      },
      "PRA-0001": {
        "schedule": {
          "WE-0": {
            "meetingDay": "WE",
            "meetingStartTime": "11:00",
            "meetingEndTime": "12:00",
            "meetingScheduleId": "0",
            "assignedRoom1": "BV",
            "assignedRoom2": "BV"
          }
        },
        "instructors": {},
        "meetingId": "PRA0001",
        "teachingMethod": "PRA",
        "sectionNumber": "0001",
        "subtitle": "",
        "cancel": "",
        "waitlist": "N",
        "deliveryMode": "INPER",
        "online": "In Person",
        "enrollmentCapacity": "22",
        "actualEnrolment": "20",
        "actualWaitlist": "0",
        "enrollmentIndicator": "",
        "meetingStatusNotes": null,
        "enrollmentControls": [
          {
            "postId": "1",
            "postCode": "*",
            "postName": "All",
            "subjectId": "1",
            "subjectCode": "*",
            "subjectName": "All",
            "designationId": "1",
            "designationCode": "*",
            "designationName": "All",
            "yearOfStudy": "*",
            "typeOfProgramId": "1",
            "typeOfProgramCode": "*",
            "typeOfProgramName": "All",
            "primaryOrgId": "1",
            "primaryOrgCode": "*",
            "primaryOrgName": "All",
            "secondaryOrgId": "1",
            "secondaryOrgCode": "*",
            "secondaryOrgName": "All",
            "assocOrgId": "1",
            "assocOrgCode": "*",
            "assocOrgName": "All",
            "adminOrgId": "1",
            "adminOrgCode": "*",
            "adminOrgName": "All"
          }
        ]
      },
      "PRA-0002": {
        "schedule": {
          "WE-0": {
            "meetingDay": "WE",
            "meetingStartTime": "12:00",
            "meetingEndTime": "13:00",
            "meetingScheduleId": "0",
            "assignedRoom1": "BV",
            "assignedRoom2": "BV"
          }
        },
        "instructors": {},
        "meetingId": "PRA0002",
        "teachingMethod": "PRA",
        "sectionNumber": "0002",
        "subtitle": "",
        "cancel": "",
        "waitlist": "N",
        "deliveryMode": "INPER",
        "online": "In Person",
        "enrollmentCapacity": "22",
        "actualEnrolment": "16",
        "actualWaitlist": "0",
        "enrollmentIndicator": "",
        "meetingStatusNotes": null,
        "enrollmentControls": [
          {
            "postId": "1",
            "postCode": "*",
            "postName": "All",
            "subjectId": "1",
            "subjectCode": "*",
            "subjectName": "All",
            "designationId": "1",
            "designationCode": "*",
            "designationName": "All",
            "yearOfStudy": "*",
            "typeOfProgramId": "1",
            "typeOfProgramCode": "*",
            "typeOfProgramName": "All",
            "primaryOrgId": "1",
            "primaryOrgCode": "*",
            "primaryOrgName": "All",
            "secondaryOrgId": "1",
            "secondaryOrgCode": "*",
            "secondaryOrgName": "All",
            "assocOrgId": "1",
            "assocOrgCode": "*",
            "assocOrgName": "All",
            "adminOrgId": "1",
            "adminOrgCode": "*",
            "adminOrgName": "All"
          }
        ]
      }
    }
  },
  "CTLA01H3-S-20261": {
    "courseId": "6818a9640982ec3a6ff6e1c0",
    "courseTitle": "Foundations in Effective Academic Communication",
    "code": "CTLA01H3",
    "courseDescription": "This highly interactive course for English Language Learners who find Academic English a challenge aims to fast-track the development of critical thinking, reading, writing and oral communication skills. Through emphasizing academic writing and rapid expansion of vocabulary, students will gain practical experience with university-level academic texts and assignment expectations.",
    "prerequisite": "No more than 10.0 credits completed. Students are required to take a diagnostic test of academic English skills to be conducted by the English Language Development Support,  Centre for Teaching and Learning, in advance of the first day of class.",
    "corequisite": "",
    "exclusion": "",
    "recommendedPreparation": "",
    "section": "S",
    "session": "20261",
    "deliveryInstructions": null,
    "breadthCategories": "Arts, Literature & Language",
    "distributionCategories": "",
    "meetings": {
      "LEC-01": {
        "schedule": {
          "TU-0": {
            "meetingDay": "TU",
            "meetingStartTime": "11:00",
            "meetingEndTime": "13:00",
            "meetingScheduleId": "0",
            "assignedRoom1": "BV",
            "assignedRoom2": "BV"
          }
        },
        "instructors": {
          "0": {
            "instructorId": "0",
            "firstName": "Elaine",
            "lastName": "Khoo"
          }
        },
        "meetingId": "LEC01",
        "teachingMethod": "LEC",
        "sectionNumber": "01",
        "subtitle": "",
        "cancel": "",
        "waitlist": "Y",
        "deliveryMode": "INPER",
        "online": "In Person",
        "enrollmentCapacity": "25",
        "actualEnrolment": "25",
        "actualWaitlist": "2",
        "enrollmentIndicator": "RP",
        "meetingStatusNotes": null,
        "enrollmentControls": [
          {
            "postId": "1",
            "postCode": "",
            "postName": "",
            "subjectId": "1",
            "subjectCode": "*",
            "subjectName": "All",
            "designationId": "1",
            "designationCode": "*",
            "designationName": "All",
            "yearOfStudy": "1",
            "typeOfProgramId": "1",
            "typeOfProgramCode": "*",
            "typeOfProgramName": "All",
            "primaryOrgId": "1",
            "primaryOrgCode": "SCAR",
            "primaryOrgName": "University of Toronto Scarborough",
            "secondaryOrgId": "1",
            "secondaryOrgCode": "*",
            "secondaryOrgName": "All",
            "assocOrgId": "1",
            "assocOrgCode": "*",
            "assocOrgName": "All",
            "adminOrgId": "1",
            "adminOrgCode": "*",
            "adminOrgName": "All"
          },
          {
            "postId": "2",
            "postCode": "",
            "postName": "",
            "subjectId": "1",
            "subjectCode": "*",
            "subjectName": "All",
            "designationId": "1",
            "designationCode": "*",
            "designationName": "All",
            "yearOfStudy": "2",
            "typeOfProgramId": "1",
            "typeOfProgramCode": "*",
            "typeOfProgramName": "All",
            "primaryOrgId": "1",
            "primaryOrgCode": "SCAR",
            "primaryOrgName": "University of Toronto Scarborough",
            "secondaryOrgId": "1",
            "secondaryOrgCode": "*",
            "secondaryOrgName": "All",
            "assocOrgId": "1",
            "assocOrgCode": "*",
            "assocOrgName": "All",
            "adminOrgId": "1",
            "adminOrgCode": "*",
            "adminOrgName": "All"
          },
          {
            "postId": "3",
            "postCode": "",
            "postName": "",
            "subjectId": "1",
            "subjectCode": "*",
            "subjectName": "All",
            "designationId": "1",
            "designationCode": "*",
            "designationName": "All",
            "yearOfStudy": "3",
            "typeOfProgramId": "1",
            "typeOfProgramCode": "*",
            "typeOfProgramName": "All",
            "primaryOrgId": "1",
            "primaryOrgCode": "SCAR",
            "primaryOrgName": "University of Toronto Scarborough",
            "secondaryOrgId": "1",
            "secondaryOrgCode": "*",
            "secondaryOrgName": "All",
            "assocOrgId": "1",
            "assocOrgCode": "*",
            "assocOrgName": "All",
            "adminOrgId": "1",
            "adminOrgCode": "*",
            "adminOrgName": "All"
          }
        ]
      },
      "PRA-0001": {
        "schedule": {
          "WE-0": {
            "meetingDay": "WE",
            "meetingStartTime": "12:00",
            "meetingEndTime": "13:00",
            "meetingScheduleId": "0",
            "assignedRoom1": "BV",
            "assignedRoom2": "BV"
          }
        },
        "instructors": {},
        "meetingId": "PRA0001",
        "teachingMethod": "PRA",
        "sectionNumber": "0001",
        "subtitle": "",
        "cancel": "",
        "waitlist": "N",
        "deliveryMode": "INPER",
        "online": "In Person",
        "enrollmentCapacity": "25",
        "actualEnrolment": "21",
        "actualWaitlist": "0",
        "enrollmentIndicator": "",
        "meetingStatusNotes": null,
        "enrollmentControls": [
          {
            "postId": "1",
            "postCode": "*",
            "postName": "All",
            "subjectId": "1",
            "subjectCode": "*",
            "subjectName": "All",
            "designationId": "1",
            "designationCode": "*",
            "designationName": "All",
            "yearOfStudy": "*",
            "typeOfProgramId": "1",
            "typeOfProgramCode": "*",
            "typeOfProgramName": "All",
            "primaryOrgId": "1",
            "primaryOrgCode": "*",
            "primaryOrgName": "All",
            "secondaryOrgId": "1",
            "secondaryOrgCode": "*",
            "secondaryOrgName": "All",
            "assocOrgId": "1",
            "assocOrgCode": "*",
            "assocOrgName": "All",
            "adminOrgId": "1",
            "adminOrgCode": "*",
            "adminOrgName": "All"
          }
        ]
      }
    }
  }
}